planetriangles/__init__.py
planetriangles/excerciser.py
planetriangles/exerciser.py
planetriangles/plane_triangles.py
planetriangles/plane_triangles_tests.py
planetriangles-1.1.dist-info/LICENSE
planetriangles-1.1.dist-info/METADATA
planetriangles-1.1.dist-info/WHEEL
planetriangles-1.1.dist-info/top_level.txt
planetriangles-1.1.dist-info/RECORD
