Metadata-Version: 2.1
Name: planetriangles
Version: 1.1
Summary: Finds the remaining sides and angles of a triangle when given enough of the sides and/or angles. Includes a command line exerciser, formatting tools, and a test suite.
Home-page: https://github.com/bob-anderson-ok/plane_triangle
Author: Bob Anderson
Author-email: bob.anderson.ok@gmail.com
License: License :: OSI Approved :: MIT License
Keywords: trigonometry,triangle,law of sines,law of cosines
Platform: UNKNOWN
Classifier: Development Status :: 5 - Production/Stable
Classifier: Intended Audience :: Science/Research
Classifier: Intended Audience :: Education
Classifier: Topic :: Scientific/Engineering :: Mathematics
Classifier: License :: OSI Approved :: MIT License
Classifier: Operating System :: OS Independent
Classifier: Programming Language :: Python :: 3
